python_programs/__init__.py
python_programs/programs.py
my_python_programs-1.0.dist-info/METADATA
my_python_programs-1.0.dist-info/WHEEL
my_python_programs-1.0.dist-info/top_level.txt
my_python_programs-1.0.dist-info/RECORD
